<?xml version="1.0" encoding="UTF-8"?>
<setting>
  <codeStyles>
    <codeStyle label="original format" comment=""/>
    <codeStyle label="plain text" comment=""/>
    <codeStyle label="csharp" comment="// " />
    <codeStyle label="cpp" comment="// " />
    <codeStyle label="css" comment="/*  */" />
    <codeStyle label="html" comment="&lt;!--  --&gt;" />
    <codeStyle label="java" comment="// " />
    <codeStyle label="javascript" comment="// " />
    <codeStyle label="json" comment="" />
    <codeStyle label="python" comment="# " />
    <codeStyle label="sql" comment="--" />
    <codeStyle label="typescript" comment="// " />
    <codeStyle label="xml" comment="&lt;!--  --&gt;" />
    <codeStyle label="yaml" comment="# " />
  </codeStyles>
  <defaultValues>
    <defaultValue id="cmbFont1" value="Microsoft YaHei Mono"></defaultValue>
    <defaultValue id="cmbFont2" value="Consolas"></defaultValue>
    <defaultValue id="cmbFont3" value="微软雅黑 Light"></defaultValue>
  </defaultValues>
  <tables>
    <table label="Gray Head Table" row="2" column="3" foreColor="000000" backColor="d8d8d8" headInLeft="false" />
    <table label="Gray Left Table" row="3" column="2" foreColor="000000" backColor="d8d8d8" headInLeft="true" />
  </tables>
  <vsCode>E:\DevelopTools\Microsoft VS Code\code.exe</vsCode>
</setting>